[
  {
    "row": 1,
    "cells": [
      "Time",
      "Brooklyn",
      "",
      "Score",
      "",
      "Toronto"
    ]
  },
  {
    "row": 3,
    "cells": [
      "11:50.0",
      "Offensive foul by N. Clowney (drawn by I. Quickley)",
      "",
      "0-0",
      "",
      ""
    ]
  },
  {
    "row": 4,
    "cells": [
      "11:50.0",
      "Turnover by N. Clowney (offensive foul)",
      "",
      "0-0",
      "",
      ""
    ]
  },
  {
    "row": 5,
    "cells": [
      "11:38.0",
      "",
      "",
      "0-0",
      "",
      "Shooting foul by T. Mann (drawn by R. Barrett)"
    ]
  },
  {
    "row": 6,
    "cells": [
      "11:38.0",
      "",
      "",
      "0-1",
      "+1",
      "R. Barrett makes free throw 1 of 2"
    ]
  },
  {
    "row": 7,
    "cells": [
      "11:38.0",
      "",
      "",
      "0-2",
      "+1",
      "R. Barrett makes free throw 2 of 2"
    ]
  },
  {
    "row": 8,
    "cells": [
      "11:29.0",
      "Personal foul by I. Quickley (drawn by N. Claxton)",
      "",
      "0-2",
      "",
      ""
    ]
  },
  {
    "row": 9,
    "cells": [
      "11:19.0",
      "Turnover by M. Porter (bad pass; steal by B. Ingram)",
      "",
      "0-2",
      "",
      ""
    ]
  },
  {
    "row": 10,
    "cells": [
      "11:12.0",
      "",
      "",
      "0-5",
      "+3",
      "S. Mamukelashvili makes 3-pt jump shot from 26 ft (assist by S. Barnes)"
    ]
  },
  {
    "row": 11,
    "cells": [
      "10:49.0",
      "M. Porter misses 2-pt jump shot from 13 ft",
      "",
      "0-5",
      "",
      ""
    ]
  },
  {
    "row": 12,
    "cells": [
      "10:47.0",
      "",
      "",
      "0-5",
      "",
      "Defensive rebound by I. Quickley"
    ]
  },
  {
    "row": 13,
    "cells": [
      "10:37.0",
      "",
      "",
      "0-7",
      "+2",
      "R. Barrett makes 2-pt layup from 1 ft (assist by S. Mamukelashvili)"
    ]
  },
  {
    "row": 14,
    "cells": [
      "10:37.0",
      "Brooklyn full timeout",
      "",
      "0-7",
      "",
      ""
    ]
  },
  {
    "row": 15,
    "cells": [
      "10:19.0",
      "N. Clowney misses 3-pt jump shot from 24 ft",
      "",
      "0-7",
      "",
      ""
    ]
  },
  {
    "row": 16,
    "cells": [
      "10:17.0",
      "Offensive rebound by Team",
      "",
      "0-7",
      "",
      ""
    ]
  },
  {
    "row": 17,
    "cells": [
      "10:04.0",
      "N. Claxton misses 2-pt jump shot from 13 ft",
      "",
      "0-7",
      "",
      ""
    ]
  },
  {
    "row": 18,
    "cells": [
      "10:01.0",
      "",
      "",
      "0-7",
      "",
      "Defensive rebound by S. Barnes"
    ]
  },
  {
    "row": 19,
    "cells": [
      "9:53.0",
      "",
      "",
      "0-10",
      "+3",
      "I. Quickley makes 3-pt jump shot from 27 ft (assist by S. Barnes)"
    ]
  },
  {
    "row": 20,
    "cells": [
      "9:28.0",
      "T. Mann misses 3-pt jump shot from 24 ft",
      "",
      "0-10",
      "",
      ""
    ]
  },
  {
    "row": 21,
    "cells": [
      "9:25.0",
      "",
      "",
      "0-10",
      "",
      "Defensive rebound by S. Mamukelashvili"
    ]
  },
  {
    "row": 22,
    "cells": [
      "9:13.0",
      "",
      "",
      "0-12",
      "+2",
      "S. Mamukelashvili makes 2-pt layup from 1 ft (assist by I. Quickley)"
    ]
  },
  {
    "row": 23,
    "cells": [
      "9:01.0",
      "N. Clowney makes 2-pt layup from 2 ft (assist by E. Dёmin)",
      "+2",
      "2-12",
      "",
      ""
    ]
  },
  {
    "row": 24,
    "cells": [
      "9:01.0",
      "Shooting foul by S. Barnes (drawn by N. Clowney)",
      "",
      "2-12",
      "",
      ""
    ]
  },
  {
    "row": 25,
    "cells": [
      "9:01.0",
      "T. Martin enters the game for T. Mann",
      "",
      "2-12",
      "",
      ""
    ]
  },
  {
    "row": 26,
    "cells": [
      "9:01.0",
      "Z. Williams enters the game for M. Porter",
      "",
      "2-12",
      "",
      ""
    ]
  },
  {
    "row": 27,
    "cells": [
      "9:01.0",
      "N. Clowney makes free throw 1 of 1",
      "+1",
      "3-12",
      "",
      ""
    ]
  },
  {
    "row": 28,
    "cells": [
      "8:40.0",
      "",
      "",
      "3-12",
      "",
      "S. Mamukelashvili misses 3-pt jump shot from 25 ft"
    ]
  },
  {
    "row": 29,
    "cells": [
      "8:37.0",
      "Defensive rebound by N. Claxton",
      "",
      "3-12",
      "",
      ""
    ]
  },
  {
    "row": 30,
    "cells": [
      "8:31.0",
      "N. Clowney misses 3-pt jump shot from 25 ft",
      "",
      "3-12",
      "",
      ""
    ]
  },
  {
    "row": 31,
    "cells": [
      "8:30.0",
      "Offensive rebound by Z. Williams",
      "",
      "3-12",
      "",
      ""
    ]
  },
  {
    "row": 32,
    "cells": [
      "8:29.0",
      "Turnover by Z. Williams (bad pass; steal by R. Barrett)",
      "",
      "3-12",
      "",
      ""
    ]
  },
  {
    "row": 33,
    "cells": [
      "8:20.0",
      "",
      "",
      "3-14",
      "+2",
      "S. Barnes makes 2-pt dunk from 1 ft (assist by R. Barrett)"
    ]
  },
  {
    "row": 34,
    "cells": [
      "8:01.0",
      "N. Clowney makes 2-pt jump shot from 6 ft",
      "+2",
      "5-14",
      "",
      ""
    ]
  },
  {
    "row": 35,
    "cells": [
      "7:46.0",
      "",
      "",
      "5-14",
      "",
      "B. Ingram misses 2-pt layup from 3 ft (block by Z. Williams)"
    ]
  },
  {
    "row": 36,
    "cells": [
      "7:46.0",
      "",
      "",
      "5-14",
      "",
      "Offensive rebound by Team"
    ]
  },
  {
    "row": 37,
    "cells": [
      "7:44.0",
      "",
      "",
      "5-14",
      "",
      "R. Barrett misses 3-pt jump shot from 24 ft"
    ]
  },
  {
    "row": 38,
    "cells": [
      "7:40.0",
      "Defensive rebound by N. Claxton",
      "",
      "5-14",
      "",
      ""
    ]
  },
  {
    "row": 39,
    "cells": [
      "7:39.0",
      "Shooting foul by B. Ingram (drawn by T. Martin)",
      "",
      "5-14",
      "",
      ""
    ]
  },
  {
    "row": 40,
    "cells": [
      "7:39.0",
      "T. Martin makes free throw 1 of 2",
      "+1",
      "6-14",
      "",
      ""
    ]
  },
  {
    "row": 41,
    "cells": [
      "7:39.0",
      "T. Martin makes free throw 2 of 2",
      "+1",
      "7-14",
      "",
      ""
    ]
  },
  {
    "row": 42,
    "cells": [
      "7:24.0",
      "",
      "",
      "7-14",
      "",
      "I. Quickley misses 3-pt jump shot from 24 ft"
    ]
  },
  {
    "row": 43,
    "cells": [
      "7:21.0",
      "Defensive rebound by N. Claxton",
      "",
      "7-14",
      "",
      ""
    ]
  },
  {
    "row": 44,
    "cells": [
      "7:11.0",
      "N. Clowney makes 2-pt layup from 5 ft (assist by T. Martin)",
      "+2",
      "9-14",
      "",
      ""
    ]
  },
  {
    "row": 45,
    "cells": [
      "6:59.0",
      "",
      "",
      "9-14",
      "",
      "R. Barrett misses 2-pt jump shot from 8 ft"
    ]
  },
  {
    "row": 46,
    "cells": [
      "6:58.0",
      "",
      "",
      "9-14",
      "",
      "Offensive rebound by Team"
    ]
  },
  {
    "row": 47,
    "cells": [
      "6:58.0",
      "",
      "",
      "9-14",
      "",
      "J. Walter enters the game for S. Barnes"
    ]
  },
  {
    "row": 48,
    "cells": [
      "6:46.0",
      "",
      "",
      "9-14",
      "",
      "B. Ingram misses 2-pt jump shot from 19 ft"
    ]
  },
  {
    "row": 49,
    "cells": [
      "6:42.0",
      "Defensive rebound by E. Dёmin",
      "",
      "9-14",
      "",
      ""
    ]
  },
  {
    "row": 50,
    "cells": [
      "6:41.0",
      "Turnover by E. Dёmin (bad pass; steal by B. Ingram)",
      "",
      "9-14",
      "",
      ""
    ]
  },
  {
    "row": 51,
    "cells": [
      "6:39.0",
      "",
      "",
      "9-14",
      "",
      "R. Barrett misses 2-pt jump shot from 2 ft"
    ]
  },
  {
    "row": 52,
    "cells": [
      "6:39.0",
      "Defensive rebound by Team",
      "",
      "9-14",
      "",
      ""
    ]
  },
  {
    "row": 53,
    "cells": [
      "6:29.0",
      "T. Martin misses 3-pt jump shot from 26 ft",
      "",
      "9-14",
      "",
      ""
    ]
  },
  {
    "row": 54,
    "cells": [
      "6:25.0",
      "",
      "",
      "9-14",
      "",
      "Defensive rebound by R. Barrett"
    ]
  },
  {
    "row": 55,
    "cells": [
      "6:20.0",
      "",
      "",
      "9-14",
      "",
      "Turnover by R. Barrett (bad pass; steal by T. Martin)"
    ]
  },
  {
    "row": 56,
    "cells": [
      "6:16.0",
      "T. Martin makes 2-pt layup from 8 ft (assist by E. Dёmin)",
      "+2",
      "11-14",
      "",
      ""
    ]
  },
  {
    "row": 57,
    "cells": [
      "6:16.0",
      "Shooting foul by S. Mamukelashvili (drawn by T. Martin)",
      "",
      "11-14",
      "",
      ""
    ]
  },
  {
    "row": 58,
    "cells": [
      "6:16.0",
      "",
      "",
      "11-14",
      "",
      "Toronto full timeout"
    ]
  },
  {
    "row": 59,
    "cells": [
      "6:16.0",
      "",
      "",
      "11-14",
      "",
      "C. Murray-Boyles enters the game for S. Mamukelashvili"
    ]
  },
  {
    "row": 60,
    "cells": [
      "6:16.0",
      "",
      "",
      "11-14",
      "",
      "J. Shead enters the game for I. Quickley"
    ]
  },
  {
    "row": 61,
    "cells": [
      "6:16.0",
      "T. Martin makes free throw 1 of 1",
      "+1",
      "12-14",
      "",
      ""
    ]
  },
  {
    "row": 62,
    "cells": [
      "6:02.0",
      "",
      "",
      "12-14",
      "",
      "B. Ingram misses 2-pt jump shot from 14 ft"
    ]
  },
  {
    "row": 63,
    "cells": [
      "5:58.0",
      "Defensive rebound by N. Clowney",
      "",
      "12-14",
      "",
      ""
    ]
  },
  {
    "row": 64,
    "cells": [
      "5:43.0",
      "N. Clowney makes 2-pt jump shot from 8 ft",
      "+2",
      "14-14",
      "",
      ""
    ]
  },
  {
    "row": 65,
    "cells": [
      "5:26.0",
      "",
      "",
      "14-17",
      "+3",
      "R. Barrett makes 3-pt jump shot from 24 ft (assist by B. Ingram)"
    ]
  },
  {
    "row": 66,
    "cells": [
      "5:15.0",
      "T. Martin makes 3-pt jump shot from 26 ft (assist by E. Dёmin)",
      "+3",
      "17-17",
      "",
      ""
    ]
  },
  {
    "row": 67,
    "cells": [
      "5:03.0",
      "",
      "",
      "17-20",
      "+3",
      "J. Walter makes 3-pt jump shot from 24 ft (assist by J. Shead)"
    ]
  },
  {
    "row": 68,
    "cells": [
      "4:45.0",
      "N. Clowney misses 3-pt jump shot from 25 ft",
      "",
      "17-20",
      "",
      ""
    ]
  },
  {
    "row": 69,
    "cells": [
      "4:43.0",
      "",
      "",
      "17-20",
      "",
      "Defensive rebound by Team"
    ]
  },
  {
    "row": 70,
    "cells": [
      "4:43.0",
      "D. Powell enters the game for E. Dёmin",
      "",
      "17-20",
      "",
      ""
    ]
  },
  {
    "row": 71,
    "cells": [
      "4:43.0",
      "",
      "",
      "17-20",
      "",
      "G. Dick enters the game for R. Barrett"
    ]
  },
  {
    "row": 72,
    "cells": [
      "4:26.0",
      "",
      "",
      "17-22",
      "+2",
      "B. Ingram makes 2-pt jump shot from 10 ft"
    ]
  },
  {
    "row": 73,
    "cells": [
      "4:10.0",
      "Shooting foul by J. Shead (drawn by T. Martin)",
      "",
      "17-22",
      "",
      ""
    ]
  },
  {
    "row": 74,
    "cells": [
      "4:10.0",
      "T. Martin makes free throw 1 of 2",
      "+1",
      "18-22",
      "",
      ""
    ]
  },
  {
    "row": 75,
    "cells": [
      "4:10.0",
      "M. Porter enters the game for N. Claxton",
      "",
      "18-22",
      "",
      ""
    ]
  },
  {
    "row": 76,
    "cells": [
      "4:10.0",
      "D. Sharpe enters the game for N. Clowney",
      "",
      "18-22",
      "",
      ""
    ]
  },
  {
    "row": 77,
    "cells": [
      "4:10.0",
      "T. Martin makes free throw 2 of 2",
      "+1",
      "19-22",
      "",
      ""
    ]
  },
  {
    "row": 78,
    "cells": [
      "3:56.0",
      "",
      "",
      "19-24",
      "+2",
      "B. Ingram makes 2-pt layup from 3 ft"
    ]
  },
  {
    "row": 79,
    "cells": [
      "3:47.0",
      "T. Martin misses 3-pt jump shot from 26 ft",
      "",
      "19-24",
      "",
      ""
    ]
  },
  {
    "row": 80,
    "cells": [
      "3:45.0",
      "Offensive rebound by D. Sharpe",
      "",
      "19-24",
      "",
      ""
    ]
  },
  {
    "row": 81,
    "cells": [
      "3:42.0",
      "D. Sharpe makes 2-pt layup at rim",
      "+2",
      "21-24",
      "",
      ""
    ]
  },
  {
    "row": 82,
    "cells": [
      "3:33.0",
      "",
      "",
      "21-27",
      "+3",
      "G. Dick makes 3-pt jump shot from 23 ft (assist by J. Shead)"
    ]
  },
  {
    "row": 83,
    "cells": [
      "3:07.0",
      "D. Powell misses 2-pt jump shot from 13 ft",
      "",
      "21-27",
      "",
      ""
    ]
  },
  {
    "row": 84,
    "cells": [
      "3:03.0",
      "",
      "",
      "21-27",
      "",
      "Defensive rebound by B. Ingram"
    ]
  },
  {
    "row": 85,
    "cells": [
      "3:01.0",
      "",
      "",
      "21-27",
      "",
      "B. Ingram misses 3-pt jump shot from 26 ft"
    ]
  },
  {
    "row": 86,
    "cells": [
      "2:59.0",
      "Defensive rebound by T. Martin",
      "",
      "21-27",
      "",
      ""
    ]
  },
  {
    "row": 87,
    "cells": [
      "2:55.0",
      "Turnover by T. Martin (out of bounds lost ball)",
      "",
      "21-27",
      "",
      ""
    ]
  },
  {
    "row": 88,
    "cells": [
      "2:55.0",
      "",
      "",
      "21-27",
      "",
      "S. Barnes enters the game for B. Ingram"
    ]
  },
  {
    "row": 89,
    "cells": [
      "2:51.0",
      "",
      "",
      "21-27",
      "",
      "Personal foul by D. Powell (drawn by J. Shead)"
    ]
  },
  {
    "row": 90,
    "cells": [
      "2:51.0",
      "T. Mann enters the game for T. Martin",
      "",
      "21-27",
      "",
      ""
    ]
  },
  {
    "row": 91,
    "cells": [
      "2:46.0",
      "",
      "",
      "21-29",
      "+2",
      "J. Walter makes 2-pt dunk from 1 ft (assist by C. Murray-Boyles)"
    ]
  },
  {
    "row": 92,
    "cells": [
      "2:23.0",
      "M. Porter misses 3-pt jump shot from 26 ft",
      "",
      "21-29",
      "",
      ""
    ]
  },
  {
    "row": 93,
    "cells": [
      "2:20.0",
      "Offensive rebound by Z. Williams",
      "",
      "21-29",
      "",
      ""
    ]
  },
  {
    "row": 94,
    "cells": [
      "2:15.0",
      "M. Porter makes 3-pt jump shot from 25 ft (assist by T. Mann)",
      "+3",
      "24-29",
      "",
      ""
    ]
  },
  {
    "row": 95,
    "cells": [
      "2:02.0",
      "",
      "",
      "24-32",
      "+3",
      "J. Walter makes 3-pt jump shot from 25 ft (assist by J. Shead)"
    ]
  },
  {
    "row": 96,
    "cells": [
      "2:02.0",
      "",
      "",
      "24-32",
      "",
      "Technical foul by D. Rajakovic"
    ]
  },
  {
    "row": 97,
    "cells": [
      "2:02.0",
      "M. Porter makes technical free throw",
      "+1",
      "25-32",
      "",
      ""
    ]
  },
  {
    "row": 98,
    "cells": [
      "1:48.0",
      "M. Porter misses 3-pt jump shot from 25 ft",
      "",
      "25-32",
      "",
      ""
    ]
  },
  {
    "row": 99,
    "cells": [
      "1:44.0",
      "",
      "",
      "25-32",
      "",
      "Defensive rebound by S. Barnes"
    ]
  },
  {
    "row": 100,
    "cells": [
      "1:29.0",
      "",
      "",
      "25-32",
      "",
      "S. Barnes misses 2-pt jump shot from 12 ft"
    ]
  },
  {
    "row": 101,
    "cells": [
      "1:26.0",
      "Defensive rebound by D. Sharpe",
      "",
      "25-32",
      "",
      ""
    ]
  },
  {
    "row": 102,
    "cells": [
      "1:21.0",
      "Shooting foul by C. Murray-Boyles (drawn by T. Mann)",
      "",
      "25-32",
      "",
      ""
    ]
  },
  {
    "row": 103,
    "cells": [
      "1:21.0",
      "T. Mann misses free throw 1 of 2",
      "",
      "25-32",
      "",
      ""
    ]
  },
  {
    "row": 104,
    "cells": [
      "1:21.0",
      "Offensive rebound by Team",
      "",
      "25-32",
      "",
      ""
    ]
  },
  {
    "row": 105,
    "cells": [
      "1:21.0",
      "J. Wilson enters the game for Z. Williams",
      "",
      "25-32",
      "",
      ""
    ]
  },
  {
    "row": 106,
    "cells": [
      "1:21.0",
      "",
      "",
      "25-32",
      "",
      "S. Mamukelashvili enters the game for C. Murray-Boyles"
    ]
  },
  {
    "row": 107,
    "cells": [
      "1:21.0",
      "",
      "",
      "25-32",
      "",
      "I. Quickley enters the game for J. Walter"
    ]
  },
  {
    "row": 108,
    "cells": [
      "1:21.0",
      "T. Mann makes free throw 2 of 2",
      "+1",
      "26-32",
      "",
      ""
    ]
  },
  {
    "row": 109,
    "cells": [
      "0:57.0",
      "",
      "",
      "26-34",
      "+2",
      "S. Barnes makes 2-pt jump shot from 17 ft"
    ]
  },
  {
    "row": 110,
    "cells": [
      "0:37.0",
      "Personal foul by J. Shead (drawn by D. Powell)",
      "",
      "26-34",
      "",
      ""
    ]
  },
  {
    "row": 111,
    "cells": [
      "0:37.0",
      "D. Powell makes free throw 1 of 2",
      "+1",
      "27-34",
      "",
      ""
    ]
  },
  {
    "row": 112,
    "cells": [
      "0:37.0",
      "N. Clowney enters the game for M. Porter",
      "",
      "27-34",
      "",
      ""
    ]
  },
  {
    "row": 113,
    "cells": [
      "0:37.0",
      "",
      "",
      "27-34",
      "",
      "R. Barrett enters the game for J. Shead"
    ]
  },
  {
    "row": 114,
    "cells": [
      "0:37.0",
      "D. Powell makes free throw 2 of 2",
      "+1",
      "28-34",
      "",
      ""
    ]
  },
  {
    "row": 115,
    "cells": [
      "0:24.0",
      "",
      "",
      "28-34",
      "",
      "S. Barnes misses 2-pt jump shot from 13 ft"
    ]
  },
  {
    "row": 116,
    "cells": [
      "0:21.0",
      "Defensive rebound by D. Powell",
      "",
      "28-34",
      "",
      ""
    ]
  },
  {
    "row": 117,
    "cells": [
      "0:00.0",
      "N. Clowney misses 2-pt jump shot from 16 ft (block by S. Barnes)",
      "",
      "28-34",
      "",
      ""
    ]
  },
  {
    "row": 118,
    "cells": [
      "0:00.0",
      "Offensive rebound by Team",
      "",
      "28-34",
      "",
      ""
    ]
  },
  {
    "row": 121,
    "cells": [
      "Time",
      "Brooklyn",
      "",
      "Score",
      "",
      "Toronto"
    ]
  },
  {
    "row": 123,
    "cells": [
      "11:47.0",
      "",
      "",
      "28-34",
      "",
      "Shooting foul by D. Sharpe (drawn by G. Dick)"
    ]
  },
  {
    "row": 124,
    "cells": [
      "11:47.0",
      "",
      "",
      "28-35",
      "+1",
      "G. Dick makes free throw 1 of 3"
    ]
  },
  {
    "row": 125,
    "cells": [
      "11:47.0",
      "",
      "",
      "28-36",
      "+1",
      "G. Dick makes free throw 2 of 3"
    ]
  },
  {
    "row": 126,
    "cells": [
      "11:47.0",
      "",
      "",
      "28-37",
      "+1",
      "G. Dick makes free throw 3 of 3"
    ]
  },
  {
    "row": 127,
    "cells": [
      "11:31.0",
      "Shooting foul by G. Dick (drawn by D. Sharpe)",
      "",
      "28-37",
      "",
      ""
    ]
  },
  {
    "row": 128,
    "cells": [
      "11:31.0",
      "D. Sharpe misses free throw 1 of 2",
      "",
      "28-37",
      "",
      ""
    ]
  },
  {
    "row": 129,
    "cells": [
      "11:31.0",
      "Offensive rebound by Team",
      "",
      "28-37",
      "",
      ""
    ]
  },
  {
    "row": 130,
    "cells": [
      "11:31.0",
      "D. Sharpe misses free throw 2 of 2",
      "",
      "28-37",
      "",
      ""
    ]
  },
  {
    "row": 131,
    "cells": [
      "11:27.0",
      "",
      "",
      "28-37",
      "",
      "Defensive rebound by I. Quickley"
    ]
  },
  {
    "row": 132,
    "cells": [
      "11:08.0",
      "",
      "",
      "28-37",
      "",
      "I. Quickley misses 2-pt jump shot from 6 ft (block by M. Porter)"
    ]
  },
  {
    "row": 133,
    "cells": [
      "11:05.0",
      "Defensive rebound by M. Porter",
      "",
      "28-37",
      "",
      ""
    ]
  },
  {
    "row": 134,
    "cells": [
      "10:47.0",
      "T. Mann misses 2-pt layup from 1 ft",
      "",
      "28-37",
      "",
      ""
    ]
  },
  {
    "row": 135,
    "cells": [
      "10:44.0",
      "",
      "",
      "28-37",
      "",
      "Defensive rebound by I. Quickley"
    ]
  },
  {
    "row": 136,
    "cells": [
      "10:42.0",
      "",
      "",
      "28-39",
      "+2",
      "G. Dick makes 2-pt dunk from 1 ft (assist by S. Barnes)"
    ]
  },
  {
    "row": 137,
    "cells": [
      "10:42.0",
      "Brooklyn full timeout",
      "",
      "28-39",
      "",
      ""
    ]
  },
  {
    "row": 138,
    "cells": [
      "10:30.0",
      "M. Porter misses 3-pt jump shot from 25 ft",
      "",
      "28-39",
      "",
      ""
    ]
  },
  {
    "row": 139,
    "cells": [
      "10:28.0",
      "Offensive rebound by T. Mann",
      "",
      "28-39",
      "",
      ""
    ]
  },
  {
    "row": 140,
    "cells": [
      "10:26.0",
      "M. Porter makes 2-pt layup from 5 ft (assist by T. Mann)",
      "+2",
      "30-39",
      "",
      ""
    ]
  },
  {
    "row": 141,
    "cells": [
      "10:07.0",
      "",
      "",
      "30-39",
      "",
      "G. Dick misses 2-pt jump shot from 13 ft"
    ]
  },
  {
    "row": 142,
    "cells": [
      "10:05.0",
      "Defensive rebound by D. Sharpe",
      "",
      "30-39",
      "",
      ""
    ]
  },
  {
    "row": 143,
    "cells": [
      "9:57.0",
      "T. Mann makes 2-pt layup from 1 ft",
      "+2",
      "32-39",
      "",
      ""
    ]
  },
  {
    "row": 144,
    "cells": [
      "9:42.0",
      "",
      "",
      "32-41",
      "+2",
      "S. Mamukelashvili makes 2-pt layup from 1 ft (assist by I. Quickley)"
    ]
  },
  {
    "row": 145,
    "cells": [
      "9:25.0",
      "J. Wilson makes 2-pt hook shot from 6 ft",
      "+2",
      "34-41",
      "",
      ""
    ]
  },
  {
    "row": 146,
    "cells": [
      "9:04.0",
      "",
      "",
      "34-43",
      "+2",
      "S. Barnes makes 2-pt layup from 2 ft (assist by G. Dick)"
    ]
  },
  {
    "row": 147,
    "cells": [
      "8:46.0",
      "M. Porter misses 2-pt jump shot from 18 ft",
      "",
      "34-43",
      "",
      ""
    ]
  },
  {
    "row": 148,
    "cells": [
      "8:46.0",
      "Offensive rebound by Team",
      "",
      "34-43",
      "",
      ""
    ]
  },
  {
    "row": 149,
    "cells": [
      "8:46.0",
      "",
      "",
      "34-43",
      "",
      "Loose ball foul by S. Mamukelashvili (drawn by D. Sharpe)"
    ]
  },
  {
    "row": 150,
    "cells": [
      "8:46.0",
      "",
      "",
      "34-43",
      "",
      "O. Agbaji enters the game for G. Dick"
    ]
  },
  {
    "row": 151,
    "cells": [
      "8:38.0",
      "M. Porter makes 3-pt jump shot from 26 ft (assist by D. Powell)",
      "+3",
      "37-43",
      "",
      ""
    ]
  },
  {
    "row": 152,
    "cells": [
      "8:28.0",
      "",
      "",
      "37-43",
      "",
      "O. Agbaji misses 3-pt jump shot from 24 ft"
    ]
  },
  {
    "row": 153,
    "cells": [
      "8:25.0",
      "",
      "",
      "37-43",
      "",
      "Offensive rebound by S. Barnes"
    ]
  },
  {
    "row": 154,
    "cells": [
      "8:24.0",
      "",
      "",
      "37-46",
      "+3",
      "R. Barrett makes 3-pt jump shot from 24 ft (assist by S. Barnes)"
    ]
  },
  {
    "row": 155,
    "cells": [
      "8:11.0",
      "D. Powell makes 2-pt jump shot from 11 ft",
      "+2",
      "39-46",
      "",
      ""
    ]
  },
  {
    "row": 156,
    "cells": [
      "8:00.0",
      "",
      "",
      "39-46",
      "",
      "Shooting foul by T. Mann (drawn by I. Quickley)"
    ]
  },
  {
    "row": 157,
    "cells": [
      "8:00.0",
      "",
      "",
      "39-47",
      "+1",
      "I. Quickley makes free throw 1 of 2"
    ]
  },
  {
    "row": 158,
    "cells": [
      "8:00.0",
      "N. Claxton enters the game for T. Mann",
      "",
      "39-47",
      "",
      ""
    ]
  },
  {
    "row": 159,
    "cells": [
      "8:00.0",
      "T. Martin enters the game for D. Powell",
      "",
      "39-47",
      "",
      ""
    ]
  },
  {
    "row": 160,
    "cells": [
      "8:00.0",
      "Z. Williams enters the game for D. Sharpe",
      "",
      "39-47",
      "",
      ""
    ]
  },
  {
    "row": 161,
    "cells": [
      "8:00.0",
      "",
      "",
      "39-48",
      "+1",
      "I. Quickley makes free throw 2 of 2"
    ]
  },
  {
    "row": 162,
    "cells": [
      "7:45.0",
      "T. Martin makes 3-pt jump shot from 29 ft (assist by M. Porter)",
      "+3",
      "42-48",
      "",
      ""
    ]
  },
  {
    "row": 163,
    "cells": [
      "7:33.0",
      "",
      "",
      "42-48",
      "",
      "Shooting foul by J. Wilson (drawn by R. Barrett)"
    ]
  },
  {
    "row": 164,
    "cells": [
      "7:33.0",
      "",
      "",
      "42-49",
      "+1",
      "R. Barrett makes free throw 1 of 2"
    ]
  },
  {
    "row": 165,
    "cells": [
      "7:33.0",
      "N. Clowney enters the game for J. Wilson",
      "",
      "42-49",
      "",
      ""
    ]
  },
  {
    "row": 166,
    "cells": [
      "7:33.0",
      "",
      "",
      "42-49",
      "",
      "B. Ingram enters the game for S. Barnes"
    ]
  },
  {
    "row": 167,
    "cells": [
      "7:33.0",
      "",
      "",
      "42-49",
      "",
      "C. Murray-Boyles enters the game for S. Mamukelashvili"
    ]
  },
  {
    "row": 168,
    "cells": [
      "7:33.0",
      "",
      "",
      "42-49",
      "",
      "J. Shead enters the game for I. Quickley"
    ]
  },
  {
    "row": 169,
    "cells": [
      "7:33.0",
      "",
      "",
      "42-50",
      "+1",
      "R. Barrett makes free throw 2 of 2"
    ]
  },
  {
    "row": 170,
    "cells": [
      "7:09.0",
      "T. Martin misses 3-pt jump shot from 25 ft",
      "",
      "42-50",
      "",
      ""
    ]
  },
  {
    "row": 171,
    "cells": [
      "7:05.0",
      "",
      "",
      "42-50",
      "",
      "Defensive rebound by R. Barrett"
    ]
  },
  {
    "row": 172,
    "cells": [
      "6:52.0",
      "",
      "",
      "42-50",
      "",
      "O. Agbaji misses 2-pt jump shot from 4 ft (block by N. Clowney)"
    ]
  },
  {
    "row": 173,
    "cells": [
      "6:51.0",
      "Defensive rebound by N. Claxton",
      "",
      "42-50",
      "",
      ""
    ]
  },
  {
    "row": 174,
    "cells": [
      "6:47.0",
      "M. Porter makes 2-pt layup from 1 ft",
      "+2",
      "44-50",
      "",
      ""
    ]
  },
  {
    "row": 175,
    "cells": [
      "6:35.0",
      "",
      "",
      "44-50",
      "",
      "Shooting foul by M. Porter (drawn by J. Shead)"
    ]
  },
  {
    "row": 176,
    "cells": [
      "6:35.0",
      "",
      "",
      "44-51",
      "+1",
      "J. Shead makes free throw 1 of 3"
    ]
  },
  {
    "row": 177,
    "cells": [
      "6:35.0",
      "",
      "",
      "44-52",
      "+1",
      "J. Shead makes free throw 2 of 3"
    ]
  },
  {
    "row": 178,
    "cells": [
      "6:35.0",
      "E. Dёmin enters the game for M. Porter",
      "",
      "44-52",
      "",
      ""
    ]
  },
  {
    "row": 179,
    "cells": [
      "6:35.0",
      "",
      "",
      "44-52",
      "",
      "I. Quickley enters the game for R. Barrett"
    ]
  },
  {
    "row": 180,
    "cells": [
      "6:35.0",
      "",
      "",
      "44-53",
      "+1",
      "J. Shead makes free throw 3 of 3"
    ]
  },
  {
    "row": 181,
    "cells": [
      "6:11.0",
      "Z. Williams misses 2-pt jump shot from 13 ft",
      "",
      "44-53",
      "",
      ""
    ]
  },
  {
    "row": 182,
    "cells": [
      "6:11.0",
      "Offensive rebound by Team",
      "",
      "44-53",
      "",
      ""
    ]
  },
  {
    "row": 183,
    "cells": [
      "6:11.0",
      "",
      "",
      "44-53",
      "",
      "Loose ball foul by O. Agbaji (drawn by N. Claxton)"
    ]
  },
  {
    "row": 184,
    "cells": [
      "6:01.0",
      "Turnover by N. Claxton (3 sec)",
      "",
      "44-53",
      "",
      ""
    ]
  },
  {
    "row": 185,
    "cells": [
      "5:40.0",
      "",
      "",
      "44-53",
      "",
      "B. Ingram misses 2-pt jump shot from 6 ft (block by N. Claxton)"
    ]
  },
  {
    "row": 186,
    "cells": [
      "5:36.0",
      "Defensive rebound by T. Martin",
      "",
      "44-53",
      "",
      ""
    ]
  },
  {
    "row": 187,
    "cells": [
      "5:26.0",
      "Z. Williams makes 3-pt jump shot from 26 ft (assist by E. Dёmin)",
      "+3",
      "47-53",
      "",
      ""
    ]
  },
  {
    "row": 188,
    "cells": [
      "5:09.0",
      "",
      "",
      "47-55",
      "+2",
      "O. Agbaji makes 2-pt layup from 1 ft (assist by B. Ingram)"
    ]
  },
  {
    "row": 189,
    "cells": [
      "4:49.0",
      "E. Dёmin misses 2-pt jump shot from 16 ft",
      "",
      "47-55",
      "",
      ""
    ]
  },
  {
    "row": 190,
    "cells": [
      "4:46.0",
      "",
      "",
      "47-55",
      "",
      "Defensive rebound by J. Shead"
    ]
  },
  {
    "row": 191,
    "cells": [
      "4:41.0",
      "",
      "",
      "47-55",
      "",
      "I. Quickley misses 3-pt jump shot from 28 ft"
    ]
  },
  {
    "row": 192,
    "cells": [
      "4:39.0",
      "",
      "",
      "47-55",
      "",
      "Offensive rebound by Team"
    ]
  },
  {
    "row": 193,
    "cells": [
      "4:39.0",
      "",
      "",
      "47-55",
      "",
      "Toronto full timeout"
    ]
  },
  {
    "row": 194,
    "cells": [
      "4:39.0",
      "",
      "",
      "47-55",
      "",
      "J. Walter enters the game for J. Shead"
    ]
  },
  {
    "row": 195,
    "cells": [
      "4:31.0",
      "",
      "",
      "47-55",
      "",
      "I. Quickley misses 2-pt jump shot from 9 ft"
    ]
  },
  {
    "row": 196,
    "cells": [
      "4:29.0",
      "Defensive rebound by N. Claxton",
      "",
      "47-55",
      "",
      ""
    ]
  },
  {
    "row": 197,
    "cells": [
      "4:20.0",
      "N. Claxton makes 2-pt jump shot from 6 ft (assist by T. Martin)",
      "+2",
      "49-55",
      "",
      ""
    ]
  },
  {
    "row": 198,
    "cells": [
      "4:13.0",
      "",
      "",
      "49-55",
      "",
      "B. Ingram misses 2-pt jump shot from 5 ft (block by Z. Williams)"
    ]
  },
  {
    "row": 199,
    "cells": [
      "4:11.0",
      "Defensive rebound by Z. Williams",
      "",
      "49-55",
      "",
      ""
    ]
  },
  {
    "row": 200,
    "cells": [
      "4:05.0",
      "T. Martin misses 2-pt layup from 5 ft",
      "",
      "49-55",
      "",
      ""
    ]
  },
  {
    "row": 201,
    "cells": [
      "4:04.0",
      "",
      "",
      "49-55",
      "",
      "Defensive rebound by J. Walter"
    ]
  },
  {
    "row": 202,
    "cells": [
      "3:56.0",
      "",
      "",
      "49-55",
      "",
      "B. Ingram misses 2-pt layup from 4 ft"
    ]
  },
  {
    "row": 203,
    "cells": [
      "3:56.0",
      "",
      "",
      "49-55",
      "",
      "Offensive rebound by B. Ingram"
    ]
  },
  {
    "row": 204,
    "cells": [
      "3:52.0",
      "",
      "",
      "49-55",
      "",
      "Turnover by B. Ingram (bad pass; steal by T. Martin)"
    ]
  },
  {
    "row": 205,
    "cells": [
      "3:48.0",
      "Turnover by N. Clowney (out of bounds lost ball)",
      "",
      "49-55",
      "",
      ""
    ]
  },
  {
    "row": 206,
    "cells": [
      "3:31.0",
      "",
      "",
      "49-57",
      "+2",
      "O. Agbaji makes 2-pt dunk from 1 ft (assist by I. Quickley)"
    ]
  },
  {
    "row": 207,
    "cells": [
      "3:17.0",
      "N. Clowney misses 3-pt jump shot from 26 ft",
      "",
      "49-57",
      "",
      ""
    ]
  },
  {
    "row": 208,
    "cells": [
      "3:14.0",
      "",
      "",
      "49-57",
      "",
      "Defensive rebound by C. Murray-Boyles"
    ]
  },
  {
    "row": 209,
    "cells": [
      "3:04.0",
      "",
      "",
      "49-60",
      "+3",
      "B. Ingram makes 3-pt jump shot from 24 ft (assist by O. Agbaji)"
    ]
  },
  {
    "row": 210,
    "cells": [
      "3:03.0",
      "Brooklyn full timeout",
      "",
      "49-60",
      "",
      ""
    ]
  },
  {
    "row": 211,
    "cells": [
      "3:03.0",
      "M. Porter enters the game for T. Martin",
      "",
      "49-60",
      "",
      ""
    ]
  },
  {
    "row": 212,
    "cells": [
      "3:03.0",
      "",
      "",
      "49-60",
      "",
      "S. Barnes enters the game for O. Agbaji"
    ]
  },
  {
    "row": 213,
    "cells": [
      "2:47.0",
      "N. Claxton makes 2-pt dunk from 1 ft",
      "+2",
      "51-60",
      "",
      ""
    ]
  },
  {
    "row": 214,
    "cells": [
      "2:33.0",
      "",
      "",
      "51-60",
      "",
      "Turnover by B. Ingram (out of bounds lost ball)"
    ]
  },
  {
    "row": 215,
    "cells": [
      "2:19.0",
      "M. Porter makes 3-pt jump shot from 26 ft (assist by N. Claxton)",
      "+3",
      "54-60",
      "",
      ""
    ]
  },
  {
    "row": 216,
    "cells": [
      "2:03.0",
      "",
      "",
      "54-60",
      "",
      "Shooting foul by N. Claxton (drawn by S. Barnes)"
    ]
  },
  {
    "row": 217,
    "cells": [
      "2:03.0",
      "",
      "",
      "54-61",
      "+1",
      "S. Barnes makes free throw 1 of 2"
    ]
  },
  {
    "row": 218,
    "cells": [
      "2:03.0",
      "",
      "",
      "54-61",
      "",
      "R. Barrett enters the game for C. Murray-Boyles"
    ]
  },
  {
    "row": 219,
    "cells": [
      "2:03.0",
      "",
      "",
      "54-61",
      "",
      "S. Mamukelashvili enters the game for J. Walter"
    ]
  },
  {
    "row": 220,
    "cells": [
      "2:03.0",
      "",
      "",
      "54-62",
      "+1",
      "S. Barnes makes free throw 2 of 2"
    ]
  },
  {
    "row": 221,
    "cells": [
      "1:44.0",
      "Z. Williams misses 3-pt jump shot from 24 ft",
      "",
      "54-62",
      "",
      ""
    ]
  },
  {
    "row": 222,
    "cells": [
      "1:42.0",
      "",
      "",
      "54-62",
      "",
      "Defensive rebound by B. Ingram"
    ]
  },
  {
    "row": 223,
    "cells": [
      "1:38.0",
      "",
      "",
      "54-62",
      "",
      "Offensive foul by R. Barrett (drawn by N. Clowney)"
    ]
  },
  {
    "row": 224,
    "cells": [
      "1:38.0",
      "",
      "",
      "54-62",
      "",
      "Turnover by R. Barrett (offensive foul)"
    ]
  },
  {
    "row": 225,
    "cells": [
      "1:21.0",
      "N. Clowney makes 2-pt dunk from 1 ft (assist by M. Porter)",
      "+2",
      "56-62",
      "",
      ""
    ]
  },
  {
    "row": 226,
    "cells": [
      "1:05.0",
      "",
      "",
      "56-62",
      "",
      "S. Barnes misses 2-pt jump shot from 8 ft"
    ]
  },
  {
    "row": 227,
    "cells": [
      "1:04.0",
      "",
      "",
      "56-62",
      "",
      "Offensive rebound by S. Barnes"
    ]
  },
  {
    "row": 228,
    "cells": [
      "1:04.0",
      "",
      "",
      "56-62",
      "",
      "Shooting foul by M. Porter (drawn by S. Barnes)"
    ]
  },
  {
    "row": 229,
    "cells": [
      "1:04.0",
      "",
      "",
      "56-62",
      "",
      "S. Barnes misses free throw 1 of 2"
    ]
  },
  {
    "row": 230,
    "cells": [
      "1:04.0",
      "",
      "",
      "56-62",
      "",
      "Offensive rebound by Team"
    ]
  },
  {
    "row": 231,
    "cells": [
      "1:04.0",
      "",
      "",
      "56-63",
      "+1",
      "S. Barnes makes free throw 2 of 2"
    ]
  },
  {
    "row": 232,
    "cells": [
      "1:04.0",
      "",
      "",
      "56-63",
      "",
      "C. Murray-Boyles enters the game for S. Mamukelashvili"
    ]
  },
  {
    "row": 233,
    "cells": [
      "0:44.0",
      "E. Dёmin misses 3-pt jump shot from 27 ft",
      "",
      "56-63",
      "",
      ""
    ]
  },
  {
    "row": 234,
    "cells": [
      "0:41.0",
      "",
      "",
      "56-63",
      "",
      "Defensive rebound by B. Ingram"
    ]
  },
  {
    "row": 235,
    "cells": [
      "0:36.0",
      "",
      "",
      "56-63",
      "",
      "Turnover by I. Quickley (bad pass; steal by M. Porter)"
    ]
  },
  {
    "row": 236,
    "cells": [
      "0:30.0",
      "M. Porter misses 2-pt jump shot from 4 ft (block by S. Barnes)",
      "",
      "56-63",
      "",
      ""
    ]
  },
  {
    "row": 237,
    "cells": [
      "0:27.0",
      "",
      "",
      "56-63",
      "",
      "Defensive rebound by I. Quickley"
    ]
  },
  {
    "row": 238,
    "cells": [
      "0:22.0",
      "",
      "",
      "56-63",
      "",
      "S. Barnes misses 2-pt jump shot from 5 ft (block by N. Claxton)"
    ]
  },
  {
    "row": 239,
    "cells": [
      "0:22.0",
      "",
      "",
      "56-63",
      "",
      "Offensive rebound by Team"
    ]
  },
  {
    "row": 240,
    "cells": [
      "0:22.0",
      "T. Mann enters the game for E. Dёmin",
      "",
      "56-63",
      "",
      ""
    ]
  },
  {
    "row": 241,
    "cells": [
      "0:22.0",
      "D. Powell enters the game for M. Porter",
      "",
      "56-63",
      "",
      ""
    ]
  },
  {
    "row": 242,
    "cells": [
      "0:22.0",
      "",
      "",
      "56-65",
      "+2",
      "C. Murray-Boyles makes 2-pt dunk from 1 ft (assist by I. Quickley)"
    ]
  },
  {
    "row": 243,
    "cells": [
      "0:02.0",
      "Shooting foul by I. Quickley (drawn by D. Powell)",
      "",
      "56-65",
      "",
      ""
    ]
  },
  {
    "row": 244,
    "cells": [
      "0:02.0",
      "D. Powell makes free throw 1 of 2",
      "+1",
      "57-65",
      "",
      ""
    ]
  },
  {
    "row": 245,
    "cells": [
      "0:02.0",
      "D. Powell makes free throw 2 of 2",
      "+1",
      "58-65",
      "",
      ""
    ]
  },
  {
    "row": 246,
    "cells": [
      "0:00.0",
      "",
      "",
      "58-65",
      "",
      "B. Ingram misses 3-pt jump shot from 27 ft"
    ]
  },
  {
    "row": 247,
    "cells": [
      "0:00.0",
      "",
      "",
      "58-65",
      "",
      "Offensive rebound by Team"
    ]
  },
  {
    "row": 250,
    "cells": [
      "Time",
      "Brooklyn",
      "",
      "Score",
      "",
      "Toronto"
    ]
  },
  {
    "row": 252,
    "cells": [
      "11:51.0",
      "",
      "",
      "58-65",
      "",
      "Shooting foul by M. Porter (drawn by R. Barrett)"
    ]
  },
  {
    "row": 253,
    "cells": [
      "11:51.0",
      "",
      "",
      "58-66",
      "+1",
      "R. Barrett makes free throw 1 of 2"
    ]
  },
  {
    "row": 254,
    "cells": [
      "11:51.0",
      "",
      "",
      "58-67",
      "+1",
      "R. Barrett makes free throw 2 of 2"
    ]
  },
  {
    "row": 255,
    "cells": [
      "11:31.0",
      "Turnover by N. Clowney (lost ball)",
      "",
      "58-67",
      "",
      ""
    ]
  },
  {
    "row": 256,
    "cells": [
      "11:31.0",
      "Loose ball foul by N. Clowney (drawn by B. Ingram)",
      "",
      "58-67",
      "",
      ""
    ]
  },
  {
    "row": 257,
    "cells": [
      "11:13.0",
      "",
      "",
      "58-67",
      "",
      "R. Barrett misses 2-pt layup from 3 ft (block by N. Clowney)"
    ]
  },
  {
    "row": 258,
    "cells": [
      "11:13.0",
      "",
      "",
      "58-67",
      "",
      "Offensive rebound by Team"
    ]
  },
  {
    "row": 259,
    "cells": [
      "11:08.0",
      "",
      "",
      "58-70",
      "+3",
      "B. Ingram makes 3-pt jump shot from 30 ft (assist by S. Mamukelashvili)"
    ]
  },
  {
    "row": 260,
    "cells": [
      "10:55.0",
      "Shooting foul by I. Quickley (drawn by N. Claxton)",
      "",
      "58-70",
      "",
      ""
    ]
  },
  {
    "row": 261,
    "cells": [
      "10:55.0",
      "N. Claxton makes free throw 1 of 2",
      "+1",
      "59-70",
      "",
      ""
    ]
  },
  {
    "row": 262,
    "cells": [
      "10:55.0",
      "N. Claxton makes free throw 2 of 2",
      "+1",
      "60-70",
      "",
      ""
    ]
  },
  {
    "row": 263,
    "cells": [
      "10:39.0",
      "",
      "",
      "60-70",
      "",
      "B. Ingram misses 3-pt jump shot from 24 ft"
    ]
  },
  {
    "row": 264,
    "cells": [
      "10:36.0",
      "Defensive rebound by M. Porter",
      "",
      "60-70",
      "",
      ""
    ]
  },
  {
    "row": 265,
    "cells": [
      "10:20.0",
      "E. Dёmin misses 3-pt jump shot from 24 ft",
      "",
      "60-70",
      "",
      ""
    ]
  },
  {
    "row": 266,
    "cells": [
      "10:17.0",
      "",
      "",
      "60-70",
      "",
      "Defensive rebound by S. Barnes"
    ]
  },
  {
    "row": 267,
    "cells": [
      "10:10.0",
      "",
      "",
      "60-70",
      "",
      "I. Quickley misses 3-pt jump shot from 27 ft"
    ]
  },
  {
    "row": 268,
    "cells": [
      "10:06.0",
      "Defensive rebound by N. Claxton",
      "",
      "60-70",
      "",
      ""
    ]
  },
  {
    "row": 269,
    "cells": [
      "9:51.0",
      "E. Dёmin makes 3-pt jump shot from 25 ft (assist by T. Mann)",
      "+3",
      "63-70",
      "",
      ""
    ]
  },
  {
    "row": 270,
    "cells": [
      "9:31.0",
      "",
      "",
      "63-70",
      "",
      "Turnover by S. Mamukelashvili (bad pass)"
    ]
  },
  {
    "row": 271,
    "cells": [
      "9:14.0",
      "M. Porter misses 2-pt jump shot from 19 ft",
      "",
      "63-70",
      "",
      ""
    ]
  },
  {
    "row": 272,
    "cells": [
      "9:11.0",
      "Offensive rebound by T. Mann",
      "",
      "63-70",
      "",
      ""
    ]
  },
  {
    "row": 273,
    "cells": [
      "9:06.0",
      "N. Clowney misses 3-pt jump shot from 26 ft",
      "",
      "63-70",
      "",
      ""
    ]
  },
  {
    "row": 274,
    "cells": [
      "9:03.0",
      "Offensive rebound by N. Claxton",
      "",
      "63-70",
      "",
      ""
    ]
  },
  {
    "row": 275,
    "cells": [
      "8:59.0",
      "E. Dёmin makes 2-pt layup at rim (assist by N. Claxton)",
      "+2",
      "65-70",
      "",
      ""
    ]
  },
  {
    "row": 276,
    "cells": [
      "8:34.0",
      "",
      "",
      "65-70",
      "",
      "I. Quickley misses 2-pt jump shot from 9 ft"
    ]
  },
  {
    "row": 277,
    "cells": [
      "8:31.0",
      "Defensive rebound by M. Porter",
      "",
      "65-70",
      "",
      ""
    ]
  },
  {
    "row": 278,
    "cells": [
      "8:20.0",
      "N. Clowney misses 2-pt jump shot from 4 ft (block by S. Barnes)",
      "",
      "65-70",
      "",
      ""
    ]
  },
  {
    "row": 279,
    "cells": [
      "8:17.0",
      "",
      "",
      "65-70",
      "",
      "Defensive rebound by I. Quickley"
    ]
  },
  {
    "row": 280,
    "cells": [
      "8:02.0",
      "",
      "",
      "65-70",
      "",
      "S. Mamukelashvili misses 2-pt jump shot from 6 ft"
    ]
  },
  {
    "row": 281,
    "cells": [
      "7:58.0",
      "Defensive rebound by N. Claxton",
      "",
      "65-70",
      "",
      ""
    ]
  },
  {
    "row": 282,
    "cells": [
      "7:44.0",
      "E. Dёmin misses 3-pt jump shot from 27 ft",
      "",
      "65-70",
      "",
      ""
    ]
  },
  {
    "row": 283,
    "cells": [
      "7:41.0",
      "Offensive rebound by N. Claxton",
      "",
      "65-70",
      "",
      ""
    ]
  },
  {
    "row": 284,
    "cells": [
      "7:38.0",
      "M. Porter misses 3-pt jump shot from 25 ft",
      "",
      "65-70",
      "",
      ""
    ]
  },
  {
    "row": 285,
    "cells": [
      "7:37.0",
      "Offensive rebound by Team",
      "",
      "65-70",
      "",
      ""
    ]
  },
  {
    "row": 286,
    "cells": [
      "7:37.0",
      "",
      "",
      "65-70",
      "",
      "Loose ball foul by I. Quickley (drawn by T. Mann)"
    ]
  },
  {
    "row": 287,
    "cells": [
      "7:37.0",
      "",
      "",
      "65-70",
      "",
      "J. Shead enters the game for I. Quickley"
    ]
  },
  {
    "row": 288,
    "cells": [
      "7:35.0",
      "Turnover by T. Mann (bad pass; steal by R. Barrett)",
      "",
      "65-70",
      "",
      ""
    ]
  },
  {
    "row": 289,
    "cells": [
      "7:32.0",
      "",
      "",
      "65-72",
      "+2",
      "R. Barrett makes 2-pt dunk from 1 ft"
    ]
  },
  {
    "row": 290,
    "cells": [
      "7:25.0",
      "Turnover by E. Dёmin (bad pass; steal by S. Mamukelashvili)",
      "",
      "65-72",
      "",
      ""
    ]
  },
  {
    "row": 291,
    "cells": [
      "7:21.0",
      "",
      "",
      "65-72",
      "",
      "S. Mamukelashvili misses 2-pt layup from 2 ft"
    ]
  },
  {
    "row": 292,
    "cells": [
      "7:17.0",
      "Defensive rebound by E. Dёmin",
      "",
      "65-72",
      "",
      ""
    ]
  },
  {
    "row": 293,
    "cells": [
      "7:15.0",
      "N. Clowney makes 2-pt layup from 1 ft (assist by T. Mann)",
      "+2",
      "67-72",
      "",
      ""
    ]
  },
  {
    "row": 294,
    "cells": [
      "7:13.0",
      "",
      "",
      "67-72",
      "",
      "Toronto full timeout"
    ]
  },
  {
    "row": 295,
    "cells": [
      "7:13.0",
      "",
      "",
      "67-72",
      "",
      "C. Murray-Boyles enters the game for R. Barrett"
    ]
  },
  {
    "row": 296,
    "cells": [
      "7:13.0",
      "",
      "",
      "67-72",
      "",
      "J. Walter enters the game for S. Mamukelashvili"
    ]
  },
  {
    "row": 297,
    "cells": [
      "7:00.0",
      "",
      "",
      "67-72",
      "",
      "Shooting foul by N. Clowney (drawn by S. Barnes)"
    ]
  },
  {
    "row": 298,
    "cells": [
      "7:00.0",
      "",
      "",
      "67-73",
      "+1",
      "S. Barnes makes free throw 1 of 2"
    ]
  },
  {
    "row": 299,
    "cells": [
      "7:00.0",
      "",
      "",
      "67-74",
      "+1",
      "S. Barnes makes free throw 2 of 2"
    ]
  },
  {
    "row": 300,
    "cells": [
      "6:41.0",
      "Shooting foul by S. Barnes (drawn by N. Clowney)",
      "",
      "67-74",
      "",
      ""
    ]
  },
  {
    "row": 301,
    "cells": [
      "6:41.0",
      "N. Clowney makes free throw 1 of 2",
      "+1",
      "68-74",
      "",
      ""
    ]
  },
  {
    "row": 302,
    "cells": [
      "6:41.0",
      "N. Clowney makes free throw 2 of 2",
      "+1",
      "69-74",
      "",
      ""
    ]
  },
  {
    "row": 303,
    "cells": [
      "6:22.0",
      "",
      "",
      "69-74",
      "",
      "S. Barnes misses 2-pt layup from 2 ft"
    ]
  },
  {
    "row": 304,
    "cells": [
      "6:21.0",
      "Defensive rebound by Team",
      "",
      "69-74",
      "",
      ""
    ]
  },
  {
    "row": 305,
    "cells": [
      "6:10.0",
      "M. Porter makes 2-pt jump shot from 23 ft (assist by N. Claxton)",
      "+2",
      "71-74",
      "",
      ""
    ]
  },
  {
    "row": 306,
    "cells": [
      "5:57.0",
      "",
      "",
      "71-74",
      "",
      "S. Barnes misses 2-pt jump shot from 8 ft"
    ]
  },
  {
    "row": 307,
    "cells": [
      "5:54.0",
      "Defensive rebound by M. Porter",
      "",
      "71-74",
      "",
      ""
    ]
  },
  {
    "row": 308,
    "cells": [
      "5:47.0",
      "Turnover by T. Mann (lost ball; steal by S. Barnes)",
      "",
      "71-74",
      "",
      ""
    ]
  },
  {
    "row": 309,
    "cells": [
      "5:40.0",
      "",
      "",
      "71-74",
      "",
      "Turnover by J. Walter (lost ball; steal by N. Clowney)"
    ]
  },
  {
    "row": 310,
    "cells": [
      "5:19.0",
      "T. Mann misses 2-pt jump shot from 9 ft",
      "",
      "71-74",
      "",
      ""
    ]
  },
  {
    "row": 311,
    "cells": [
      "5:17.0",
      "",
      "",
      "71-74",
      "",
      "Defensive rebound by B. Ingram"
    ]
  },
  {
    "row": 312,
    "cells": [
      "5:10.0",
      "",
      "",
      "71-74",
      "",
      "B. Ingram misses 2-pt jump shot from 18 ft"
    ]
  },
  {
    "row": 313,
    "cells": [
      "5:08.0",
      "Defensive rebound by M. Porter",
      "",
      "71-74",
      "",
      ""
    ]
  },
  {
    "row": 314,
    "cells": [
      "4:50.0",
      "Shooting foul by S. Barnes (drawn by M. Porter)",
      "",
      "71-74",
      "",
      ""
    ]
  },
  {
    "row": 315,
    "cells": [
      "4:50.0",
      "Instant Replay",
      "",
      "71-74",
      "",
      ""
    ]
  },
  {
    "row": 316,
    "cells": [
      "4:50.0",
      "T. Martin enters the game for N. Clowney",
      "",
      "71-74",
      "",
      ""
    ]
  },
  {
    "row": 317,
    "cells": [
      "4:50.0",
      "D. Powell enters the game for E. Dёmin",
      "",
      "71-74",
      "",
      ""
    ]
  },
  {
    "row": 318,
    "cells": [
      "4:50.0",
      "Z. Williams enters the game for T. Mann",
      "",
      "71-74",
      "",
      ""
    ]
  },
  {
    "row": 319,
    "cells": [
      "4:50.0",
      "",
      "",
      "71-74",
      "",
      "G. Dick enters the game for S. Barnes"
    ]
  },
  {
    "row": 320,
    "cells": [
      "4:50.0",
      "M. Porter makes free throw 1 of 2",
      "+1",
      "72-74",
      "",
      ""
    ]
  },
  {
    "row": 321,
    "cells": [
      "4:50.0",
      "M. Porter makes free throw 2 of 2",
      "+1",
      "73-74",
      "",
      ""
    ]
  },
  {
    "row": 322,
    "cells": [
      "4:34.0",
      "",
      "",
      "73-76",
      "+2",
      "J. Walter makes 2-pt dunk from 2 ft (assist by G. Dick)"
    ]
  },
  {
    "row": 323,
    "cells": [
      "4:19.0",
      "N. Claxton makes 2-pt dunk from 1 ft (assist by T. Martin)",
      "+2",
      "75-76",
      "",
      ""
    ]
  },
  {
    "row": 324,
    "cells": [
      "4:13.0",
      "",
      "",
      "75-76",
      "",
      "Shooting foul by T. Martin (drawn by J. Shead)"
    ]
  },
  {
    "row": 325,
    "cells": [
      "4:13.0",
      "",
      "",
      "75-76",
      "",
      "J. Shead misses free throw 1 of 2"
    ]
  },
  {
    "row": 326,
    "cells": [
      "4:13.0",
      "",
      "",
      "75-76",
      "",
      "Offensive rebound by Team"
    ]
  },
  {
    "row": 327,
    "cells": [
      "4:13.0",
      "D. Sharpe enters the game for N. Claxton",
      "",
      "75-76",
      "",
      ""
    ]
  },
  {
    "row": 328,
    "cells": [
      "4:13.0",
      "",
      "",
      "75-77",
      "+1",
      "J. Shead makes free throw 2 of 2"
    ]
  },
  {
    "row": 329,
    "cells": [
      "3:52.0",
      "Turnover by T. Martin (bad pass)",
      "",
      "75-77",
      "",
      ""
    ]
  },
  {
    "row": 330,
    "cells": [
      "3:40.0",
      "",
      "",
      "75-80",
      "+3",
      "J. Walter makes 3-pt jump shot from 26 ft (assist by G. Dick)"
    ]
  },
  {
    "row": 331,
    "cells": [
      "3:21.0",
      "T. Martin makes 3-pt jump shot from 27 ft (assist by D. Powell)",
      "+3",
      "78-80",
      "",
      ""
    ]
  },
  {
    "row": 332,
    "cells": [
      "3:01.0",
      "",
      "",
      "78-80",
      "",
      "J. Shead misses 3-pt jump shot from 26 ft"
    ]
  },
  {
    "row": 333,
    "cells": [
      "3:00.0",
      "",
      "",
      "78-80",
      "",
      "Offensive rebound by Team"
    ]
  },
  {
    "row": 334,
    "cells": [
      "3:00.0",
      "N. Clowney enters the game for M. Porter",
      "",
      "78-80",
      "",
      ""
    ]
  },
  {
    "row": 335,
    "cells": [
      "2:54.0",
      "",
      "",
      "78-80",
      "",
      "B. Ingram misses 2-pt jump shot from 10 ft"
    ]
  },
  {
    "row": 336,
    "cells": [
      "2:50.0",
      "Defensive rebound by T. Martin",
      "",
      "78-80",
      "",
      ""
    ]
  },
  {
    "row": 337,
    "cells": [
      "2:33.0",
      "Turnover by T. Martin (lost ball; steal by G. Dick)",
      "",
      "78-80",
      "",
      ""
    ]
  },
  {
    "row": 338,
    "cells": [
      "2:27.0",
      "",
      "",
      "78-83",
      "+3",
      "J. Walter makes 3-pt jump shot from 25 ft (assist by J. Shead)"
    ]
  },
  {
    "row": 339,
    "cells": [
      "2:08.0",
      "Offensive foul by D. Sharpe (drawn by J. Shead)",
      "",
      "78-83",
      "",
      ""
    ]
  },
  {
    "row": 340,
    "cells": [
      "2:08.0",
      "Turnover by D. Sharpe (offensive foul)",
      "",
      "78-83",
      "",
      ""
    ]
  },
  {
    "row": 341,
    "cells": [
      "2:08.0",
      "Brooklyn full timeout",
      "",
      "78-83",
      "",
      ""
    ]
  },
  {
    "row": 342,
    "cells": [
      "2:08.0",
      "",
      "",
      "78-83",
      "",
      "O. Agbaji enters the game for B. Ingram"
    ]
  },
  {
    "row": 343,
    "cells": [
      "2:08.0",
      "",
      "",
      "78-83",
      "",
      "S. Barnes enters the game for C. Murray-Boyles"
    ]
  },
  {
    "row": 344,
    "cells": [
      "1:48.0",
      "",
      "",
      "78-83",
      "",
      "J. Shead misses 2-pt jump shot from 9 ft"
    ]
  },
  {
    "row": 345,
    "cells": [
      "1:45.0",
      "Defensive rebound by D. Sharpe",
      "",
      "78-83",
      "",
      ""
    ]
  },
  {
    "row": 346,
    "cells": [
      "1:28.0",
      "Turnover by D. Powell (lost ball; steal by J. Walter)",
      "",
      "78-83",
      "",
      ""
    ]
  },
  {
    "row": 347,
    "cells": [
      "1:26.0",
      "",
      "",
      "78-83",
      "",
      "J. Walter misses 3-pt jump shot from 25 ft"
    ]
  },
  {
    "row": 348,
    "cells": [
      "1:23.0",
      "Defensive rebound by D. Sharpe",
      "",
      "78-83",
      "",
      ""
    ]
  },
  {
    "row": 349,
    "cells": [
      "1:04.0",
      "T. Martin misses 2-pt jump shot from 8 ft",
      "",
      "78-83",
      "",
      ""
    ]
  },
  {
    "row": 350,
    "cells": [
      "1:02.0",
      "Offensive rebound by T. Martin",
      "",
      "78-83",
      "",
      ""
    ]
  },
  {
    "row": 351,
    "cells": [
      "1:01.0",
      "T. Martin misses 2-pt layup from 2 ft",
      "",
      "78-83",
      "",
      ""
    ]
  },
  {
    "row": 352,
    "cells": [
      "1:00.0",
      "",
      "",
      "78-83",
      "",
      "Defensive rebound by S. Barnes"
    ]
  },
  {
    "row": 353,
    "cells": [
      "0:52.0",
      "",
      "",
      "78-83",
      "",
      "J. Shead misses 3-pt jump shot from 27 ft"
    ]
  },
  {
    "row": 354,
    "cells": [
      "0:50.0",
      "Defensive rebound by D. Sharpe",
      "",
      "78-83",
      "",
      ""
    ]
  },
  {
    "row": 355,
    "cells": [
      "0:50.0",
      "Technical foul by J. Fernández Torres",
      "",
      "78-83",
      "",
      ""
    ]
  },
  {
    "row": 356,
    "cells": [
      "0:50.0",
      "",
      "",
      "78-84",
      "+1",
      "G. Dick makes technical free throw"
    ]
  },
  {
    "row": 357,
    "cells": [
      "0:35.0",
      "Personal foul by O. Agbaji (drawn by Z. Williams)",
      "",
      "78-84",
      "",
      ""
    ]
  },
  {
    "row": 358,
    "cells": [
      "0:35.0",
      "Z. Williams makes free throw 1 of 2",
      "+1",
      "79-84",
      "",
      ""
    ]
  },
  {
    "row": 359,
    "cells": [
      "0:35.0",
      "Z. Williams makes free throw 2 of 2",
      "+1",
      "80-84",
      "",
      ""
    ]
  },
  {
    "row": 360,
    "cells": [
      "0:29.0",
      "",
      "",
      "80-84",
      "",
      "Personal foul by D. Powell (drawn by J. Shead)"
    ]
  },
  {
    "row": 361,
    "cells": [
      "0:29.0",
      "",
      "",
      "80-85",
      "+1",
      "J. Shead makes free throw 1 of 2"
    ]
  },
  {
    "row": 362,
    "cells": [
      "0:29.0",
      "M. Porter enters the game for D. Powell",
      "",
      "80-85",
      "",
      ""
    ]
  },
  {
    "row": 363,
    "cells": [
      "0:29.0",
      "",
      "",
      "80-85",
      "",
      "C. Murray-Boyles enters the game for G. Dick"
    ]
  },
  {
    "row": 364,
    "cells": [
      "0:29.0",
      "",
      "",
      "80-85",
      "",
      "J. Shead misses free throw 2 of 2"
    ]
  },
  {
    "row": 365,
    "cells": [
      "0:27.0",
      "Defensive rebound by T. Martin",
      "",
      "80-85",
      "",
      ""
    ]
  },
  {
    "row": 366,
    "cells": [
      "0:13.0",
      "D. Sharpe makes 2-pt hook shot from 4 ft (assist by M. Porter)",
      "+2",
      "82-85",
      "",
      ""
    ]
  },
  {
    "row": 367,
    "cells": [
      "0:00.0",
      "",
      "",
      "82-87",
      "+2",
      "S. Barnes makes 2-pt jump shot from 10 ft (assist by J. Shead)"
    ]
  },
  {
    "row": 368,
    "cells": [
      "0:00.0",
      "",
      "",
      "82-87",
      "",
      "Instant Replay (Request: Ruling Stands)"
    ]
  },
  {
    "row": 371,
    "cells": [
      "Time",
      "Brooklyn",
      "",
      "Score",
      "",
      "Toronto"
    ]
  },
  {
    "row": 373,
    "cells": [
      "11:38.0",
      "M. Porter makes 3-pt jump shot from 29 ft",
      "+3",
      "85-87",
      "",
      ""
    ]
  },
  {
    "row": 374,
    "cells": [
      "11:22.0",
      "",
      "",
      "85-87",
      "",
      "G. Dick misses 3-pt jump shot from 24 ft"
    ]
  },
  {
    "row": 375,
    "cells": [
      "11:18.0",
      "",
      "",
      "85-87",
      "",
      "Offensive rebound by O. Agbaji"
    ]
  },
  {
    "row": 376,
    "cells": [
      "11:17.0",
      "",
      "",
      "85-89",
      "+2",
      "O. Agbaji makes 2-pt layup at rim"
    ]
  },
  {
    "row": 377,
    "cells": [
      "11:03.0",
      "T. Martin makes 2-pt layup at rim",
      "+2",
      "87-89",
      "",
      ""
    ]
  },
  {
    "row": 378,
    "cells": [
      "10:50.0",
      "",
      "",
      "87-89",
      "",
      "G. Dick misses 3-pt jump shot from 25 ft"
    ]
  },
  {
    "row": 379,
    "cells": [
      "10:46.0",
      "",
      "",
      "87-89",
      "",
      "Offensive rebound by S. Barnes"
    ]
  },
  {
    "row": 380,
    "cells": [
      "10:45.0",
      "",
      "",
      "87-91",
      "+2",
      "S. Barnes makes 2-pt layup at rim"
    ]
  },
  {
    "row": 381,
    "cells": [
      "10:33.0",
      "T. Martin makes 3-pt jump shot from 26 ft",
      "+3",
      "90-91",
      "",
      ""
    ]
  },
  {
    "row": 382,
    "cells": [
      "10:15.0",
      "",
      "",
      "90-94",
      "+3",
      "G. Dick makes 3-pt jump shot from 26 ft (assist by O. Agbaji)"
    ]
  },
  {
    "row": 383,
    "cells": [
      "9:57.0",
      "Personal foul by G. Dick (drawn by D. Sharpe)",
      "",
      "90-94",
      "",
      ""
    ]
  },
  {
    "row": 384,
    "cells": [
      "9:47.0",
      "Shooting foul by O. Agbaji (drawn by D. Sharpe)",
      "",
      "90-94",
      "",
      ""
    ]
  },
  {
    "row": 385,
    "cells": [
      "9:47.0",
      "D. Sharpe makes free throw 1 of 2",
      "+1",
      "91-94",
      "",
      ""
    ]
  },
  {
    "row": 386,
    "cells": [
      "9:47.0",
      "D. Sharpe misses free throw 2 of 2",
      "",
      "91-94",
      "",
      ""
    ]
  },
  {
    "row": 387,
    "cells": [
      "9:44.0",
      "",
      "",
      "91-94",
      "",
      "Defensive rebound by O. Agbaji"
    ]
  },
  {
    "row": 388,
    "cells": [
      "9:30.0",
      "",
      "",
      "91-94",
      "",
      "I. Quickley misses 2-pt jump shot from 20 ft"
    ]
  },
  {
    "row": 389,
    "cells": [
      "9:27.0",
      "Defensive rebound by Z. Williams",
      "",
      "91-94",
      "",
      ""
    ]
  },
  {
    "row": 390,
    "cells": [
      "9:16.0",
      "T. Martin makes 3-pt jump shot from 26 ft (assist by D. Sharpe)",
      "+3",
      "94-94",
      "",
      ""
    ]
  },
  {
    "row": 391,
    "cells": [
      "9:15.0",
      "",
      "",
      "94-94",
      "",
      "Toronto full timeout"
    ]
  },
  {
    "row": 392,
    "cells": [
      "9:15.0",
      "",
      "",
      "94-94",
      "",
      "B. Ingram enters the game for S. Barnes"
    ]
  },
  {
    "row": 393,
    "cells": [
      "9:15.0",
      "",
      "",
      "94-94",
      "",
      "S. Mamukelashvili enters the game for J. Walter"
    ]
  },
  {
    "row": 394,
    "cells": [
      "8:52.0",
      "",
      "",
      "94-96",
      "+2",
      "B. Ingram makes 2-pt jump shot from 8 ft"
    ]
  },
  {
    "row": 395,
    "cells": [
      "8:30.0",
      "Shooting foul by S. Mamukelashvili (drawn by N. Clowney)",
      "",
      "94-96",
      "",
      ""
    ]
  },
  {
    "row": 396,
    "cells": [
      "8:30.0",
      "N. Clowney makes free throw 1 of 2",
      "+1",
      "95-96",
      "",
      ""
    ]
  },
  {
    "row": 397,
    "cells": [
      "8:30.0",
      "N. Clowney makes free throw 2 of 2",
      "+1",
      "96-96",
      "",
      ""
    ]
  },
  {
    "row": 398,
    "cells": [
      "8:08.0",
      "",
      "",
      "96-96",
      "",
      "Turnover by B. Ingram (bad pass)"
    ]
  },
  {
    "row": 399,
    "cells": [
      "7:58.0",
      "Turnover by D. Sharpe (lost ball; steal by I. Quickley)",
      "",
      "96-96",
      "",
      ""
    ]
  },
  {
    "row": 400,
    "cells": [
      "7:55.0",
      "",
      "",
      "96-98",
      "+2",
      "I. Quickley makes 2-pt dunk at rim"
    ]
  },
  {
    "row": 401,
    "cells": [
      "7:40.0",
      "Shooting foul by I. Quickley (drawn by T. Martin)",
      "",
      "96-98",
      "",
      ""
    ]
  },
  {
    "row": 402,
    "cells": [
      "7:40.0",
      "T. Martin makes free throw 1 of 2",
      "+1",
      "97-98",
      "",
      ""
    ]
  },
  {
    "row": 403,
    "cells": [
      "7:40.0",
      "N. Claxton enters the game for M. Porter",
      "",
      "97-98",
      "",
      ""
    ]
  },
  {
    "row": 404,
    "cells": [
      "7:40.0",
      "E. Dёmin enters the game for D. Sharpe",
      "",
      "97-98",
      "",
      ""
    ]
  },
  {
    "row": 405,
    "cells": [
      "7:40.0",
      "",
      "",
      "97-98",
      "",
      "J. Shead enters the game for I. Quickley"
    ]
  },
  {
    "row": 406,
    "cells": [
      "7:40.0",
      "T. Martin makes free throw 2 of 2",
      "+1",
      "98-98",
      "",
      ""
    ]
  },
  {
    "row": 407,
    "cells": [
      "7:19.0",
      "",
      "",
      "98-98",
      "",
      "O. Agbaji misses 2-pt layup from 3 ft"
    ]
  },
  {
    "row": 408,
    "cells": [
      "7:17.0",
      "Defensive rebound by T. Martin",
      "",
      "98-98",
      "",
      ""
    ]
  },
  {
    "row": 409,
    "cells": [
      "7:06.0",
      "N. Clowney misses 3-pt jump shot from 26 ft",
      "",
      "98-98",
      "",
      ""
    ]
  },
  {
    "row": 410,
    "cells": [
      "7:04.0",
      "",
      "",
      "98-98",
      "",
      "Defensive rebound by S. Mamukelashvili"
    ]
  },
  {
    "row": 411,
    "cells": [
      "6:55.0",
      "",
      "",
      "98-100",
      "+2",
      "J. Shead makes 2-pt layup at rim (assist by B. Ingram)"
    ]
  },
  {
    "row": 412,
    "cells": [
      "6:42.0",
      "Turnover by T. Martin (lost ball; steal by G. Dick)",
      "",
      "98-100",
      "",
      ""
    ]
  },
  {
    "row": 413,
    "cells": [
      "6:37.0",
      "",
      "",
      "98-100",
      "",
      "Personal foul by N. Clowney (drawn by O. Agbaji)"
    ]
  },
  {
    "row": 414,
    "cells": [
      "6:37.0",
      "T. Mann enters the game for T. Martin",
      "",
      "98-100",
      "",
      ""
    ]
  },
  {
    "row": 415,
    "cells": [
      "6:21.0",
      "",
      "",
      "98-100",
      "",
      "O. Agbaji misses 2-pt layup from 1 ft"
    ]
  },
  {
    "row": 416,
    "cells": [
      "6:19.0",
      "Defensive rebound by E. Dёmin",
      "",
      "98-100",
      "",
      ""
    ]
  },
  {
    "row": 417,
    "cells": [
      "6:12.0",
      "Shooting foul by S. Mamukelashvili (drawn by N. Clowney)",
      "",
      "98-100",
      "",
      ""
    ]
  },
  {
    "row": 418,
    "cells": [
      "6:12.0",
      "N. Clowney makes free throw 1 of 2",
      "+1",
      "99-100",
      "",
      ""
    ]
  },
  {
    "row": 419,
    "cells": [
      "6:12.0",
      "",
      "",
      "99-100",
      "",
      "S. Barnes enters the game for O. Agbaji"
    ]
  },
  {
    "row": 420,
    "cells": [
      "6:12.0",
      "N. Clowney makes free throw 2 of 2",
      "+1",
      "100-100",
      "",
      ""
    ]
  },
  {
    "row": 421,
    "cells": [
      "6:01.0",
      "",
      "",
      "100-100",
      "",
      "Personal foul by E. Dёmin (drawn by B. Ingram)"
    ]
  },
  {
    "row": 422,
    "cells": [
      "5:54.0",
      "",
      "",
      "100-102",
      "+2",
      "B. Ingram makes 2-pt jump shot from 15 ft (assist by J. Shead)"
    ]
  },
  {
    "row": 423,
    "cells": [
      "5:31.0",
      "N. Claxton makes 2-pt layup from 1 ft (assist by T. Mann)",
      "+2",
      "102-102",
      "",
      ""
    ]
  },
  {
    "row": 424,
    "cells": [
      "5:10.0",
      "",
      "",
      "102-104",
      "+2",
      "S. Barnes makes 2-pt dunk from 1 ft (assist by J. Shead)"
    ]
  },
  {
    "row": 425,
    "cells": [
      "4:58.0",
      "E. Dёmin misses 2-pt jump shot from 20 ft",
      "",
      "102-104",
      "",
      ""
    ]
  },
  {
    "row": 426,
    "cells": [
      "4:56.0",
      "",
      "",
      "102-104",
      "",
      "Defensive rebound by G. Dick"
    ]
  },
  {
    "row": 427,
    "cells": [
      "4:36.0",
      "",
      "",
      "102-104",
      "",
      "S. Mamukelashvili misses 3-pt jump shot from 23 ft"
    ]
  },
  {
    "row": 428,
    "cells": [
      "4:33.0",
      "Defensive rebound by Team",
      "",
      "102-104",
      "",
      ""
    ]
  },
  {
    "row": 429,
    "cells": [
      "4:33.0",
      "M. Porter enters the game for N. Clowney",
      "",
      "102-104",
      "",
      ""
    ]
  },
  {
    "row": 430,
    "cells": [
      "4:33.0",
      "D. Powell enters the game for Z. Williams",
      "",
      "102-104",
      "",
      ""
    ]
  },
  {
    "row": 431,
    "cells": [
      "4:33.0",
      "",
      "",
      "102-104",
      "",
      "J. Walter enters the game for G. Dick"
    ]
  },
  {
    "row": 432,
    "cells": [
      "4:25.0",
      "E. Dёmin misses 2-pt layup from 5 ft (block by S. Barnes)",
      "",
      "102-104",
      "",
      ""
    ]
  },
  {
    "row": 433,
    "cells": [
      "4:24.0",
      "Offensive rebound by M. Porter",
      "",
      "102-104",
      "",
      ""
    ]
  },
  {
    "row": 434,
    "cells": [
      "4:24.0",
      "M. Porter makes 2-pt layup at rim",
      "+2",
      "104-104",
      "",
      ""
    ]
  },
  {
    "row": 435,
    "cells": [
      "3:59.0",
      "",
      "",
      "104-104",
      "",
      "Shooting foul by D. Powell (drawn by J. Shead)"
    ]
  },
  {
    "row": 436,
    "cells": [
      "3:59.0",
      "",
      "",
      "104-105",
      "+1",
      "J. Shead makes free throw 1 of 2"
    ]
  },
  {
    "row": 437,
    "cells": [
      "3:59.0",
      "",
      "",
      "104-106",
      "+1",
      "J. Shead makes free throw 2 of 2"
    ]
  },
  {
    "row": 438,
    "cells": [
      "3:42.0",
      "E. Dёmin misses 3-pt jump shot from 26 ft",
      "",
      "104-106",
      "",
      ""
    ]
  },
  {
    "row": 439,
    "cells": [
      "3:40.0",
      "Offensive rebound by N. Claxton",
      "",
      "104-106",
      "",
      ""
    ]
  },
  {
    "row": 440,
    "cells": [
      "3:34.0",
      "N. Claxton misses 2-pt hook shot from 6 ft",
      "",
      "104-106",
      "",
      ""
    ]
  },
  {
    "row": 441,
    "cells": [
      "3:32.0",
      "",
      "",
      "104-106",
      "",
      "Defensive rebound by S. Mamukelashvili"
    ]
  },
  {
    "row": 442,
    "cells": [
      "3:31.0",
      "",
      "",
      "104-106",
      "",
      "Toronto full timeout"
    ]
  },
  {
    "row": 443,
    "cells": [
      "3:31.0",
      "N. Clowney enters the game for E. Dёmin",
      "",
      "104-106",
      "",
      ""
    ]
  },
  {
    "row": 444,
    "cells": [
      "3:31.0",
      "T. Martin enters the game for M. Porter",
      "",
      "104-106",
      "",
      ""
    ]
  },
  {
    "row": 445,
    "cells": [
      "3:31.0",
      "Z. Williams enters the game for D. Powell",
      "",
      "104-106",
      "",
      ""
    ]
  },
  {
    "row": 446,
    "cells": [
      "3:31.0",
      "",
      "",
      "104-106",
      "",
      "I. Quickley enters the game for J. Walter"
    ]
  },
  {
    "row": 447,
    "cells": [
      "3:17.0",
      "",
      "",
      "104-109",
      "+3",
      "I. Quickley makes 3-pt jump shot from 27 ft (assist by J. Shead)"
    ]
  },
  {
    "row": 448,
    "cells": [
      "3:15.0",
      "Brooklyn full timeout",
      "",
      "104-109",
      "",
      ""
    ]
  },
  {
    "row": 449,
    "cells": [
      "3:15.0",
      "E. Dёmin enters the game for T. Mann",
      "",
      "104-109",
      "",
      ""
    ]
  },
  {
    "row": 450,
    "cells": [
      "3:15.0",
      "M. Porter enters the game for Z. Williams",
      "",
      "104-109",
      "",
      ""
    ]
  },
  {
    "row": 451,
    "cells": [
      "2:59.0",
      "T. Martin misses 3-pt jump shot from 30 ft",
      "",
      "104-109",
      "",
      ""
    ]
  },
  {
    "row": 452,
    "cells": [
      "2:55.0",
      "",
      "",
      "104-109",
      "",
      "Defensive rebound by I. Quickley"
    ]
  },
  {
    "row": 453,
    "cells": [
      "2:34.0",
      "",
      "",
      "104-109",
      "",
      "Personal foul by N. Clowney (drawn by B. Ingram)"
    ]
  },
  {
    "row": 454,
    "cells": [
      "2:22.0",
      "",
      "",
      "104-112",
      "+3",
      "I. Quickley makes 3-pt jump shot from 26 ft (assist by B. Ingram)"
    ]
  },
  {
    "row": 455,
    "cells": [
      "2:03.0",
      "Turnover by N. Clowney (bad pass; steal by S. Barnes)",
      "",
      "104-112",
      "",
      ""
    ]
  },
  {
    "row": 456,
    "cells": [
      "2:01.0",
      "",
      "",
      "104-112",
      "",
      "S. Barnes misses 2-pt layup from 3 ft"
    ]
  },
  {
    "row": 457,
    "cells": [
      "2:00.0",
      "",
      "",
      "104-112",
      "",
      "Offensive rebound by S. Mamukelashvili"
    ]
  },
  {
    "row": 458,
    "cells": [
      "2:00.0",
      "",
      "",
      "104-114",
      "+2",
      "S. Mamukelashvili makes 2-pt layup at rim"
    ]
  },
  {
    "row": 459,
    "cells": [
      "1:53.0",
      "E. Dёmin misses 3-pt jump shot from 30 ft",
      "",
      "104-114",
      "",
      ""
    ]
  },
  {
    "row": 460,
    "cells": [
      "1:49.0",
      "",
      "",
      "104-114",
      "",
      "Defensive rebound by B. Ingram"
    ]
  },
  {
    "row": 461,
    "cells": [
      "1:27.0",
      "",
      "",
      "104-114",
      "",
      "B. Ingram misses 2-pt jump shot from 15 ft"
    ]
  },
  {
    "row": 462,
    "cells": [
      "1:22.0",
      "Defensive rebound by N. Claxton",
      "",
      "104-114",
      "",
      ""
    ]
  },
  {
    "row": 463,
    "cells": [
      "1:15.0",
      "N. Clowney makes 3-pt jump shot from 25 ft (assist by M. Porter)",
      "+3",
      "107-114",
      "",
      ""
    ]
  },
  {
    "row": 464,
    "cells": [
      "0:54.0",
      "",
      "",
      "107-117",
      "+3",
      "S. Mamukelashvili makes 3-pt jump shot from 27 ft (assist by J. Shead)"
    ]
  },
  {
    "row": 465,
    "cells": [
      "0:46.0",
      "M. Porter misses 3-pt jump shot from 25 ft",
      "",
      "107-117",
      "",
      ""
    ]
  },
  {
    "row": 466,
    "cells": [
      "0:43.0",
      "",
      "",
      "107-117",
      "",
      "Defensive rebound by I. Quickley"
    ]
  },
  {
    "row": 467,
    "cells": [
      "0:29.0",
      "",
      "",
      "107-117",
      "",
      "Personal foul by N. Claxton (drawn by J. Shead)"
    ]
  },
  {
    "row": 468,
    "cells": [
      "0:29.0",
      "",
      "",
      "107-118",
      "+1",
      "J. Shead makes free throw 1 of 2"
    ]
  },
  {
    "row": 469,
    "cells": [
      "0:29.0",
      "",
      "",
      "107-119",
      "+1",
      "J. Shead makes free throw 2 of 2"
    ]
  },
  {
    "row": 470,
    "cells": [
      "0:24.0",
      "Turnover by N. Clowney (bad pass; steal by J. Shead)",
      "",
      "107-119",
      "",
      ""
    ]
  },
  {
    "row": 471,
    "cells": [
      "0:22.0",
      "",
      "",
      "107-119",
      "",
      "Turnover by J. Shead (bad pass; steal by N. Clowney)"
    ]
  },
  {
    "row": 472,
    "cells": [
      "0:18.0",
      "M. Porter makes 2-pt layup from 1 ft (assist by N. Clowney)",
      "+2",
      "109-119",
      "",
      ""
    ]
  }
]